backtestify/__init__.py
backtestify/account.py
backtestify/backtester.py
backtestify/cfd.py
backtestify/event.py
backtestify/event_execution_context.py
backtestify/event_execution_strategy.py
backtestify/event_type.py
backtestify/financial_instrument.py
backtestify/instrument_type.py
backtestify/signal_event.py
backtestify/signal_type.py
backtestify/strategy.py
backtestify/trade.py
backtestify/trade_executor.py
backtestify/trade_state.py
backtestify-0.1.6.dist-info/LICENSE
backtestify-0.1.6.dist-info/METADATA
backtestify-0.1.6.dist-info/WHEEL
backtestify-0.1.6.dist-info/top_level.txt
backtestify-0.1.6.dist-info/RECORD
