Metadata-Version: 2.1
Name: backtestify
Version: 0.1.6
Summary: A package for backtesting trading strategies
Home-page: https://github.com/EladioRocha/backtestify
Author: Eladio Rocha Vizcaino
Author-email: eladio.rocha99@gmail.com
License: Apache License 2.0
Project-URL: Bug Tracker, https://github.com/EladioRocha/backtestify/issues
License-File: LICENSE
Requires-Dist: pandas
